Metadata-Version: 2.1
Name: openwakeword
Version: 0.5.1
Summary: An open-source audio wake word (or phrase) detection framework with a focus on performance and simplicity
Home-page: https://pypi.org/project/openwakeword
Author: David Scripka
Author-email: David Scripka <david.scripka@gmail.com>
Project-URL: Homepage, https://github.com/dscripka/openWakeWord
Classifier: Programming Language :: Python :: 3
Classifier: License :: OSI Approved :: Apache Software License
Classifier: Operating System :: OS Independent
Requires-Python: >=3.7
License-File: LICENSE
Requires-Dist: onnxruntime <2,>=1.10.0
Requires-Dist: tqdm <5.0,>=4.0
Requires-Dist: scipy <2,>=1.3
Requires-Dist: scikit-learn <2,>=1
Requires-Dist: tflite-runtime <3,>=2.8.0 ; platform_system == "Linux"
Provides-Extra: full
Requires-Dist: mutagen <2,>=1.46.0 ; extra == 'full'
Requires-Dist: speechbrain <1,>=0.5.13 ; extra == 'full'
Requires-Dist: pytest <8,>=7.2.0 ; extra == 'full'
Requires-Dist: pytest-cov <3,>=2.10.1 ; extra == 'full'
Requires-Dist: pytest-flake8 <2,>=1.1.1 ; extra == 'full'
Requires-Dist: pytest-mypy <1,>=0.10.0 ; extra == 'full'
Requires-Dist: plotext <6,>=5.2.7 ; extra == 'full'
Requires-Dist: sounddevice <1,>=0.4.1 ; extra == 'full'
Provides-Extra: test
Requires-Dist: pytest <8,>=7.2.0 ; extra == 'test'
Requires-Dist: pytest-cov <3,>=2.10.1 ; extra == 'test'
Requires-Dist: pytest-flake8 <2,>=1.1.1 ; extra == 'test'
Requires-Dist: flake8 <4.1,>=4.0 ; extra == 'test'
Requires-Dist: pytest-mypy <1,>=0.10.0 ; extra == 'test'
Requires-Dist: mock <6,>=5.1 ; extra == 'test'
Requires-Dist: types-mock <6,>=5.1 ; extra == 'test'
